dakirby/__init__.py
dakirby/cli.py
dakirby/core/a2jauthor.py
dakirby/core/common.py
dakirby/core/docassemble.py
dakirby/core/hotdocs.py
dakirby-0.0.2.dist-info/LICENSE
dakirby-0.0.2.dist-info/METADATA
dakirby-0.0.2.dist-info/WHEEL
dakirby-0.0.2.dist-info/entry_points.txt
dakirby-0.0.2.dist-info/top_level.txt
dakirby-0.0.2.dist-info/RECORD
